{
    "version": "1.10.5",
    "description": "Mindolph is an open source personal knowledge management software for all desktop platforms.",
    "homepage": "https://github.com/mindolph/Mindolph",
    "license": "GPL-3.0",
    "url": "https://github.com/mindolph/Mindolph/releases/download/v1.10.5/Mindolph-1.10.5.msi",
    "hash": "feb827aec9752186ee70d1741f79c9d979d1c89af2a6d90528feb4caba3b6139",
    "extract_dir": "Mindolph",
    "shortcuts": [
        [
            "Mindolph.exe",
            "Mindolph"
        ]
    ],
    "checkver": "github",
    "autoupdate": {
        "url": "https://github.com/mindolph/Mindolph/releases/download/v$version/Mindolph-$version.msi"
    }
}
